{
  "unversionedId": "Secrets/Integrate Vault with helm",
  "id": "Secrets/Integrate Vault with helm",
  "title": "Integrate Vault with helm",
  "description": "",
  "source": "@site/docs/Secrets/Integrate Vault with helm.md",
  "sourceDirName": "Secrets",
  "slug": "/Secrets/Integrate Vault with helm",
  "permalink": "/docs/Secrets/Integrate Vault with helm",
  "draft": false,
  "editUrl": "https://github.com/Chamssiddine/azure-devops-aks/docs/Secrets/Integrate Vault with helm.md",
  "tags": [],
  "version": "current",
  "sidebarPosition": 4,
  "frontMatter": {
    "sidebar_position": 4
  },
  "sidebar": "tutorialSidebar",
  "previous": {
    "title": "Configure Vault Cluster",
    "permalink": "/docs/Secrets/Configure Vault"
  },
  "next": {
    "title": "Integrate Vault with Jenkins",
    "permalink": "/docs/Secrets/Integrate Vault with Jenkins"
  }
}